{
  "project_info": {
    "project_number": "95596102705",
    "firebase_url": "https://e-tution-plus.firebaseio.com",
    "project_id": "e-tution-plus",
    "storage_bucket": "e-tution-plus.appspot.com"
  },
  "client": [
    {
      "client_info": {
        "mobilesdk_app_id": "1:95596102705:android:02b1cf2b7d5cd1c5",
        "android_client_info": {
          "package_name": "com.elitlabs.attendancemanagment"
        }
      },
      "oauth_client": [
        {
          "client_id": "95596102705-t354eookhbos0qfh2h7su50sk6a3sbt8.apps.googleusercontent.com",
          "client_type": 1,
          "android_info": {
            "package_name": "com.elitlabs.attendancemanagment",
            "certificate_hash": "fc0574dfb5635bf0d0055cfba4e718f03592967a"
          }
        },
        {
          "client_id": "95596102705-lsclovo08rdcg217dg68dm76983f4210.apps.googleusercontent.com",
          "client_type": 3
        }
      ],
      "api_key": [
        {
          "current_key": "AIzaSyAhZC91XhETAnx6v6i_gd01lIGIvNTbwOY"
        },
        {
          "current_key": "AIzaSyAhZC91XhETAnx6v6i_gd01lIGIvNTbwOY"
        }
      ],
      "services": {
        "analytics_service": {
          "status": 1
        },
        "appinvite_service": {
          "status": 2,
          "other_platform_oauth_client": [
            {
              "client_id": "95596102705-lsclovo08rdcg217dg68dm76983f4210.apps.googleusercontent.com",
              "client_type": 3
            }
          ]
        },
        "ads_service": {
          "status": 2
        }
      }
    }
  ],
  "configuration_version": "1"
}